wagtail_impersonate/__init__.py
wagtail_impersonate/apps.py
wagtail_impersonate/wagtail_hooks.py
wagtail_impersonate-0.1.0.dist-info/LICENSE
wagtail_impersonate-0.1.0.dist-info/METADATA
wagtail_impersonate-0.1.0.dist-info/WHEEL
wagtail_impersonate-0.1.0.dist-info/top_level.txt
wagtail_impersonate-0.1.0.dist-info/RECORD
