Metadata-Version: 2.1
Name: wagtail-impersonate
Version: 0.1.0
Summary: Wagtail integration for django-impersonate
Author-email: Stepan Pliaskin <stepan@plyask.in>
License: Copyright (c) 2024, Stepan Pliaskin <stepan@plyask.in>
Project-URL: homepage, https://github.com/ToJIka4/wagtail-impersonate
Project-URL: repository, https://github.com/ToJIka4/wagtail-impersonate
Keywords: wagtail,django,impersonate
Classifier: Development Status :: 3 - Alpha
Classifier: Intended Audience :: Developers
Classifier: License :: OSI Approved :: BSD License
Classifier: Operating System :: OS Independent
Classifier: Programming Language :: Python
Classifier: Programming Language :: Python :: 3
Classifier: Programming Language :: Python :: 3.8
Classifier: Programming Language :: Python :: 3.9
Classifier: Programming Language :: Python :: 3.10
Classifier: Programming Language :: Python :: 3.11
Classifier: Programming Language :: Python :: 3.12
Classifier: Framework :: Django
Classifier: Framework :: Django :: 4.2
Classifier: Framework :: Django :: 5.0
Classifier: Framework :: Wagtail
Classifier: Topic :: Software Development :: Libraries :: Python Modules
Requires-Python: >=3.1
License-File: LICENSE
Requires-Dist: django-impersonate>=1.9.4
Requires-Dist: wagtail>=6.1
